{
    "id":  5,
    "name":  "Hikvision DS-2CE15A2P-IR",
    "image":  "img/cameras/img_10.jpg",
    "productDetails":  [
                           {
                               "Name":  "Тип камеры",
                               "Value":  "Аналоговая, наружная"
                           },
                           {
                               "Name":  "Матрица",
                               "Value":  "1/3\u0027\u0027 DIS"
                           },
                           {
                               "Name":  "Разрешение",
                               "Value":  "700 ТВЛ"
                           },
                           {
                               "Name":  "Видеовыход",
                               "Value":  "1Vp-р композитный выход"
                           },
                           {
                               "Name":  "Светочувствительность",
                               "Value":  "0.01 люкс"
                           },
                           {
                               "Name":  "Объектив",
                               "Value":  "Фиксированный, 3.6мм, 68,4⁰"
                           },
                           {
                               "Name":  "ИК-подсветка",
                               "Value":  "20м"
                           },
                           {
                               "Name":  "Механический ИК-фильтр",
                               "Value":  "Нет"
                           },
                           {
                               "Name":  "Автодиафрагм",
                               "Value":  "Нет"
                           },
                           {
                               "Name":  "OSD меню",
                               "Value":  "Нет"
                           },
                           {
                               "Name":  "Тип крепления",
                               "Value":  "Потолочный, настенный"
                           },
                           {
                               "Name":  "Защита",
                               "Value":  "IP66"
                           },
                           {
                               "Name":  "Рабочая температура",
                               "Value":  "-40 ⁰C ~ + 60 ⁰C"
                           },
                           {
                               "Name":  "Питание",
                               "Value":  "DC 12V"
                           },
                           {
                               "Name":  "Габариты",
                               "Value":  "70мм x 150мм"
                           },
                           {
                               "Name":  "Вес",
                               "Value":  "360г"
                           },
                           {
                               "Name":  "Комплектация",
                               "Value":  "Видеокамера, монтажный набор, монтажный спец. ключ, инструкция."
                           },
                           {
                               "Name":  "Гарантия",
                               "Value":  "12 месяцев"
                           }
                       ],
    "manufacturer":  "Hikvision"
}
