{"id":164,"name":"Групповая клавиатура Satel INT-SF-BSB","image":"img/security/img_137.jpg","productDetails":[{"Name":"Совместимост","Value":"INTEGRA, INTEGRA Plus"},{"Name":"Номинальное напряжение питания (±15%","Value":"12 В DC"},{"Name":"Максимальное потребление ток","Value":"40 мА"},{"Name":"Потребление тока в режиме готовност","Value":"20 мА"},{"Name":"Максимальный ток релейного выхода (резистивная нагрузка","Value":"2 A / 24 В D"},{"Name":"Класс среды по стандарту EN50130-","Value":"I"},{"Name":"Диапазон рабочих температу","Value":"-10 °C...+55 °"},{"Name":"Максимальная влажность воздух","Value":"93±3"},{"Name":"Габаритные размеры корпус","Value":"80 x 143 x 25 мм"},{"Name":"Ве","Value":"180 г"}],"manufacturer":"Satel"}