{
    "id":  166,
    "name":  "Магнитоконтактный датчик Satel B-1M BR (10 штук)",
    "image":  "img/security/img_43.jpg",
    "productDetails":  [
                           {
                               "Name":  "Максимальный коммутируемый то",
                               "Value":  "0,5 A"
                           },
                           {
                               "Name":  "Максимальное коммутируемое напряжение геркон",
                               "Value":  "100 В"
                           },
                           {
                               "Name":  "Расстояние замыкания контактов геркон",
                               "Value":  "30 мм"
                           },
                           {
                               "Name":  "Расстояние размыкания контактов геркон",
                               "Value":  "33 мм"
                           },
                           {
                               "Name":  "Габаритные размеры корпус",
                               "Value":  "51 x 9 мм"
                           }
                       ],
    "manufacturer":  "Satel"
}
