{"id":92,"name":"Звуковой оповещатель Satel SPW-250 R/BL/O","image":"img/security/img_234.jpg","productDetails":[{"Name":"Напряжение питания (±15%","Value":"12 В DC"},{"Name":"Максимальное потребление тока - акустическая сигнализаци","Value":"90 мА"},{"Name":"Среднее потребление тока в режиме готовности (±10%","Value":"100 мкА"},{"Name":"Громкость звук","Value":"120 дБ"},{"Name":"Класс среды по стандарту EN50130-","Value":"I"},{"Name":"Диапазон рабочих температу","Value":"-10…+55 °"},{"Name":"Максимальная влажность воздух","Value":"93 ±3"},{"Name":"Габаритные размеры корпус","Value":"87 x 133 x 37 мм"},{"Name":"Ве","Value":"160 г"}],"manufacturer":"Satel"}